pptemp/__init__.py
pptemp/pptemp.py
pptemp-0.1.0.dist-info/LICENSE.md
pptemp-0.1.0.dist-info/METADATA
pptemp-0.1.0.dist-info/WHEEL
pptemp-0.1.0.dist-info/top_level.txt
pptemp-0.1.0.dist-info/RECORD
