Metadata-Version: 2.1
Name: pptemp
Version: 0.1.0
Summary: It enables you to make powerpoint files in a simple python commands.
Home-page: https://github.com/Ameyanagi/pptemp
Download-URL: https://github.com/Ameyanagi/pptemp
Author: Ameyanagi
Author-email: 
License: MIT
Keywords: powerpoint,pptx
Classifier: Development Status :: 3 - Alpha
Classifier: Intended Audience :: Developers
Classifier: License :: OSI Approved :: MIT License
Classifier: Operating System :: OS Independent
Classifier: Programming Language :: Python :: 3
Classifier: Programming Language :: Python :: 3.7
Classifier: Programming Language :: Python :: 3.8
Classifier: Programming Language :: Python :: 3.9
Classifier: Programming Language :: Python :: 3.10
Classifier: Topic :: Software Development :: Libraries :: Python Modules
Requires-Python: >=3.7
License-File: LICENSE.md
Requires-Dist: python-pptx
Requires-Dist: pandas
Requires-Dist: numpy
Requires-Dist: lxml
Requires-Dist: Pillow
Requires-Dist: tqdm
